pyprogress/__init__.py
pyprogress/__main__.py
pyprogress/countoutput.py
pyprogress-0.1.4.0.dist-info/DESCRIPTION.rst
pyprogress-0.1.4.0.dist-info/METADATA
pyprogress-0.1.4.0.dist-info/RECORD
pyprogress-0.1.4.0.dist-info/WHEEL
pyprogress-0.1.4.0.dist-info/entry_points.txt
pyprogress-0.1.4.0.dist-info/metadata.json
pyprogress-0.1.4.0.dist-info/top_level.txt
