Metadata-Version: 2.0
Name: pyprogress
Version: 0.1.4.0
Summary: Various command line progress bars, spinners and counters including threaded versions
Home-page: https://github.com/mouckatron/pyprogress
Author: Graham Moucka
Author-email: mouckatron@gmail.com
License: MIT
Keywords: progress spinner counter cli timer completion
Platform: UNKNOWN
Classifier: Environment :: Console
Classifier: License :: OSI Approved :: MIT License
Classifier: Natural Language :: English
Classifier: Programming Language :: Python
Classifier: Programming Language :: Python :: 2.7
Classifier: Programming Language :: Python :: 3
Classifier: Programming Language :: Python :: 3.0
Classifier: Programming Language :: Python :: 3.1
Classifier: Programming Language :: Python :: 3.2
Classifier: Programming Language :: Python :: 3.3
Classifier: Programming Language :: Python :: 3.4
Classifier: Programming Language :: Python :: 3.5
Classifier: Programming Language :: Python :: 3.6
